nothingpy/__init__.py
nothingpy/nothing.py
nothingpy-0.1.3.dist-info/METADATA
nothingpy-0.1.3.dist-info/WHEEL
nothingpy-0.1.3.dist-info/licenses/LICENSE
nothingpy-0.1.3.dist-info/RECORD
